chaplinfilter/__init__.py
chaplinfilter/filter.py
chaplinfilter-0.1.4.dist-info/METADATA
chaplinfilter-0.1.4.dist-info/RECORD
chaplinfilter-0.1.4.dist-info/WHEEL
chaplinfilter-0.1.4.dist-info/top_level.txt
