Metadata-Version: 2.1
Name: chaplinfilter
Version: 0.1.4
Summary: UNKNOWN
Home-page: UNKNOWN
Author: Guy R. Davies
Author-email: grd349@gmail.com
License: MIT
Platform: UNKNOWN
Requires-Dist: numpy
Requires-Dist: scikit-learn
Requires-Dist: pandas
